mechmean/__init__.py
mechmean/approximation.py
mechmean/approximation_docstrings.py
mechmean/example_input.py
mechmean/fabric_tensors.py
mechmean/hill_polarization.py
mechmean/hill_polarization_alternatives.py
mechmean/material.py
mechmean/operators.py
mechmean/orientation_averager.py
mechmean/orientation_averager_alternatives.py
mechmean/utils.py
mechmean-0.1.0.dist-info/LICENSE
mechmean-0.1.0.dist-info/METADATA
mechmean-0.1.0.dist-info/WHEEL
mechmean-0.1.0.dist-info/top_level.txt
mechmean-0.1.0.dist-info/RECORD
