Metadata-Version: 2.1
Name: mechmean
Version: 0.1.0
Summary: Mechmean contains selected mean field methods in the context of continuum mechanics with special focus on orientation averaged homogenization
Home-page: https://github.com/JulianKarlBauer/mechmean/
Author: Julian Karl Bauer
Author-email: juliankarlbauer@gmx.de
License: UNKNOWN
Platform: UNKNOWN
Classifier: Programming Language :: Python :: 3
Classifier: Operating System :: OS Independent
License-File: LICENSE
Requires-Dist: numpy
Requires-Dist: scipy
Requires-Dist: mechkit (>=0.2.6)
